gcigps/__init__.py
gcigps/messages.py
gcigps/parser.py
gcigps-2023.8.13.dist-info/METADATA
gcigps-2023.8.13.dist-info/WHEEL
gcigps-2023.8.13.dist-info/RECORD
