Metadata-Version: 2.1
Name: gcigps
Version: 2023.8.13
Summary: parsing gps messages
Home-page: https://pypi.org/project/gcigps/
License: MIT
Keywords: ins,navigation,gps
Author: walchko
Author-email: walchko@users.noreply.github.com
Requires-Python: >=3.10
Classifier: Development Status :: 4 - Beta
Classifier: Intended Audience :: Developers
Classifier: License :: OSI Approved :: MIT License
Classifier: Operating System :: OS Independent
Classifier: Programming Language :: Python :: 3
Classifier: Programming Language :: Python :: 3.10
Classifier: Programming Language :: Python :: 3.11
Classifier: Topic :: Software Development :: Libraries
Classifier: Topic :: Software Development :: Libraries :: Application Frameworks
Classifier: Topic :: Software Development :: Libraries :: Python Modules
Project-URL: Repository, https://github.com/the-guild-of-calamitous-intent/gciGps
